xueanquan/__init__.py
xueanquan/method.py
xueanquan-1.1.dist-info/LICENSE
xueanquan-1.1.dist-info/METADATA
xueanquan-1.1.dist-info/WHEEL
xueanquan-1.1.dist-info/entry_points.txt
xueanquan-1.1.dist-info/top_level.txt
xueanquan-1.1.dist-info/RECORD
