Metadata-Version: 2.1
Name: xueanquan
Version: 1.1
Summary: Do xueanquan courses automatically
Home-page: https://houtar.coding.net/public/xueanquan/python/git/files
Author: Houtarchat
Author-email: admin@houtarchat.ml
License: GNU GENERAL PUBLIC LICENSE
Platform: UNKNOWN
Requires-Python: >=3
Requires-Dist: requests
